synchro/__init__.py
synchro/threads.py
synchropy-0.0.5.dist-info/LICENSE
synchropy-0.0.5.dist-info/METADATA
synchropy-0.0.5.dist-info/WHEEL
synchropy-0.0.5.dist-info/top_level.txt
synchropy-0.0.5.dist-info/RECORD
