Metadata-Version: 2.1
Name: synchropy
Version: 0.0.5
Summary: A library for easy synchronizing
Author-email: trollmii <trollmii@outlook.com>
License: Apache License
Requires-Python: >=3.8
License-File: LICENSE
